deeptable/__init__.py
deeptable/_base_client.py
deeptable/_client.py
deeptable/_compat.py
deeptable/_constants.py
deeptable/_exceptions.py
deeptable/_files.py
deeptable/_models.py
deeptable/_qs.py
deeptable/_resource.py
deeptable/_response.py
deeptable/_streaming.py
deeptable/_types.py
deeptable/_version.py
deeptable/pagination.py
deeptable/py.typed
deeptable/_utils/__init__.py
deeptable/_utils/_compat.py
deeptable/_utils/_datetime_parse.py
deeptable/_utils/_json.py
deeptable/_utils/_logs.py
deeptable/_utils/_proxy.py
deeptable/_utils/_reflection.py
deeptable/_utils/_resources_proxy.py
deeptable/_utils/_streams.py
deeptable/_utils/_sync.py
deeptable/_utils/_transform.py
deeptable/_utils/_typing.py
deeptable/_utils/_utils.py
deeptable/lib/.keep
deeptable/resources/__init__.py
deeptable/resources/files.py
deeptable/resources/structured_sheets/__init__.py
deeptable/resources/structured_sheets/structured_sheets.py
deeptable/resources/structured_sheets/tables.py
deeptable/types/__init__.py
deeptable/types/file.py
deeptable/types/file_delete_response.py
deeptable/types/file_list_params.py
deeptable/types/file_upload_params.py
deeptable/types/structured_sheet_create_params.py
deeptable/types/structured_sheet_delete_response.py
deeptable/types/structured_sheet_download_params.py
deeptable/types/structured_sheet_list_params.py
deeptable/types/structured_sheet_response.py
deeptable/types/structured_sheets/__init__.py
deeptable/types/structured_sheets/table_download_params.py
deeptable/types/structured_sheets/table_list_params.py
deeptable/types/structured_sheets/table_response.py
deeptable-0.1.0b2.dist-info/METADATA
deeptable-0.1.0b2.dist-info/WHEEL
deeptable-0.1.0b2.dist-info/licenses/LICENSE
deeptable-0.1.0b2.dist-info/RECORD
